metplotpy/__init__.py
metplotpy/contributed/__init__.py
metplotpy/contributed/blocking_s2s/CBL_plot.py
metplotpy/contributed/blocking_s2s/__init__.py
metplotpy/contributed/blocking_s2s/plot_blocking.py
metplotpy/contributed/grid_to_grid/__init__.py
metplotpy/contributed/grid_to_grid/plot_grid_to_grid.py
metplotpy/contributed/hovmoeller/__init__.py
metplotpy/contributed/hovmoeller/hovmoeller_calc.py
metplotpy/contributed/hovmoeller/hovmoeller_plotly.py
metplotpy/contributed/hovmoeller/run_hovmoeller.py
metplotpy/contributed/mjo_rmm_omi/__init__.py
metplotpy/contributed/mjo_rmm_omi/plot_mjo_indices.py
metplotpy/contributed/series_analysis/__init__.py
metplotpy/contributed/series_analysis/animate_series_by_lead_all.py
metplotpy/contributed/series_analysis/animate_utilities.py
metplotpy/contributed/series_analysis/plot_series_by_grouping.py
metplotpy/contributed/series_analysis/plot_series_by_init.py
metplotpy/contributed/series_analysis/plot_series_by_lead_all.py
metplotpy/contributed/spacetime_plot/__init__.py
metplotpy/contributed/spacetime_plot/spacetime_plot.py
metplotpy/contributed/spacetime_plot/spectra_plot_coh2.py
metplotpy/contributed/spacetime_plot/spectra_plot_power.py
metplotpy/contributed/stratosphere_diagnostics/__init__.py
metplotpy/contributed/stratosphere_diagnostics/stratosphere_diagnostics.py
metplotpy/contributed/tc_s2s_panel/__init__.py
metplotpy/contributed/tc_s2s_panel/plot_tc_s2s_panel.py
metplotpy/contributed/weather_regime/__init__.py
metplotpy/contributed/weather_regime/plot_weather_regime.py
metplotpy/plots/__init__.py
metplotpy/plots/base_plot.py
metplotpy/plots/config.py
metplotpy/plots/constants.py
metplotpy/plots/series.py
metplotpy/plots/setup.py
metplotpy/plots/util.py
metplotpy/plots/bar/__init__.py
metplotpy/plots/bar/bar.py
metplotpy/plots/bar/bar_config.py
metplotpy/plots/bar/bar_series.py
metplotpy/plots/box/__init__.py
metplotpy/plots/box/box.py
metplotpy/plots/box/box_config.py
metplotpy/plots/box/box_series.py
metplotpy-1.1.0.dist-info/METADATA
metplotpy-1.1.0.dist-info/WHEEL
metplotpy-1.1.0.dist-info/top_level.txt
metplotpy-1.1.0.dist-info/RECORD
