Metadata-Version: 2.1
Name: metplotpy
Version: 1.1.0
Summary: plotting package for METplus
Home-page: https://github.com/dtcenter/METplotpy
Author: METplus
Author-email: met-help@ucar.edu
License: UNKNOWN
Platform: UNKNOWN
Classifier: Programming Language :: Python :: 3
Classifier: License :: OSI Approved :: MIT License
Classifier: Operating System :: OS Independent
Requires-Python: >=3.6
